e2D/__init__.py
e2D/commons.py
e2D/cvectors.c
e2D/cvectors.cp313-win_amd64.pyd
e2D/cvectors.pxd
e2D/cvectors.pyx
e2D/devices.py
e2D/plots.py
e2D/shapes.py
e2D/text_renderer.py
e2D/vectors.py
e2D/shaders/curve_fragment.glsl
e2D/shaders/curve_vertex.glsl
e2D/shaders/line_instanced_vertex.glsl
e2D/shaders/plot_grid_fragment.glsl
e2D/shaders/plot_grid_vertex.glsl
e2D/shaders/segment_fragment.glsl
e2D/shaders/segment_vertex.glsl
e2D/shaders/stream_fragment.glsl
e2D/shaders/stream_shift_compute.glsl
e2D/shaders/stream_vertex.glsl
e2d-2.0.0.dist-info/licenses/LICENSE
e2d-2.0.0.dist-info/METADATA
e2d-2.0.0.dist-info/WHEEL
e2d-2.0.0.dist-info/top_level.txt
e2d-2.0.0.dist-info/RECORD
