Metadata-Version: 2.4
Name: e2D
Version: 2.0.0
Summary: High-performance 2D graphics and math library with ultra-optimized vector operations
Home-page: https://github.com/marick-py/e2D
Author: Riccardo Mariani
Author-email: Riccardo Mariani <ricomari2006@gmail.com>
License: MIT
Project-URL: Homepage, https://github.com/marick-py/e2D
Project-URL: Repository, https://github.com/marick-py/e2D
Project-URL: Issues, https://github.com/marick-py/e2D/issues
Keywords: vector,2d,simulation,performance,cython,numpy,moderngl,games,graphics
Classifier: Development Status :: 4 - Beta
Classifier: Intended Audience :: Developers
Classifier: Intended Audience :: Science/Research
Classifier: License :: OSI Approved :: MIT License
Classifier: Programming Language :: Python :: 3
Classifier: Programming Language :: Python :: 3.9
Classifier: Programming Language :: Python :: 3.10
Classifier: Programming Language :: Python :: 3.11
Classifier: Programming Language :: Python :: 3.12
Classifier: Programming Language :: Python :: 3.13
Classifier: Programming Language :: Cython
Classifier: Programming Language :: C
Classifier: Topic :: Games/Entertainment
Classifier: Topic :: Scientific/Engineering
Classifier: Topic :: Software Development :: Libraries :: Python Modules
Classifier: Topic :: Multimedia :: Graphics
Requires-Python: >=3.9
License-File: LICENSE
Requires-Dist: numpy>=1.19.0
Requires-Dist: pygame
Requires-Dist: moderngl
Requires-Dist: glfw
Provides-Extra: dev
Requires-Dist: build; extra == "dev"
Requires-Dist: twine; extra == "dev"
Requires-Dist: pytest; extra == "dev"
Requires-Dist: black; extra == "dev"
Requires-Dist: mypy; extra == "dev"
Provides-Extra: performance
Requires-Dist: cython>=0.29.0; extra == "performance"
Dynamic: license-file
